Workbook

Sheet How to use
A1: QA Checklist: Comparative Accuracy of Improper Payment Estimation Methods
A2: Human reviewer's checklist. Read qa/README.md first.
A4: Purpose | B4: This workbook records everything a human reviewer checks: an independent re-run with date-stamped logs, a code review of every key assumption, and a check that the results are represented correctly. It is the evidence behind the signed sign-off form.
A5: Order of work | B5: 1. Reviewer sheet 2. Re-run (Checklist section B) and Run log sheet 3. Code review (section C) 4. Results (section D) 5. Tests, data security, documentation (E-G) 6. Issues log 7. Close-out (section H) and sign-off form.
A6: Cells you fill in | B6: Only the yellow cells. On the Checklist: Status, Date checked, Initials, Evidence, Issue ID and Notes. Grey and blue cells are fixed text or formulas; do not edit them.
A7: Status values | B7: Not started: not yet checked. Pass: checked and matches the expected result. Fail: checked and does not match; log it on the Issues log and enter its ID. N/A: does not apply (explain why in Notes).
A8: Dates | B8: Enter dates as YYYY-MM-DD (for example 2026-10-21). Date-times on the Run log as YYYY-MM-DD HH:MM.
A9: Evidence | B9: Where the proof is: a file path in your re-run folder (for example logs/run_2026-10-21_093000/stage7_01_pytest.log), a screenshot file name in review/, or a short description.
A10: Commands | B10: Commands are written for macOS and Linux (.venv/bin/python). On Windows, replace .venv/bin/python with .venv\Scripts\python and forward slashes in file paths with backslashes.
A11: Wildcards | B11: In 'Where to look', * means 'any folder or file name here'; for example */errors/sql/*.sql means the errors/sql folder of every program.
A12: Example of a completed row | B12: Status: Pass | Date checked: 2026-10-21 | Initials: JD | Evidence: logs/run_2026-10-21_093000/stage7_01_pytest.log | Issue ID: (blank) | Notes: 38 passed in 89 s.
A13: When you finish | B13: The Summary sheet shows progress and whether the review is ready to sign. Save this file as QA_Checklist_<date>_<initials>.xlsx in qa/reruns/<date>_<initials>/review/.
A15: Legend
A16: Yellow | B16: You fill this in
A17: Light blue | B17: Section heading or fixed text
A18: Green / red status | B18: Pass turns green; Fail turns red automatically

Sheet Summary
A1: Summary
A2: Calculated from the Checklist and Issues log. Nothing to fill in here.
A4: Section | B4: Tasks | C4: Pass | D4: Fail | E4: N/A | F4: Not started | G4: Complete (%)
A5: A. Setup and independence | B5: =COUNTIF(Checklist!$B$6:$B$102,"Setup and independence") | C5: =COUNTIFS(Checklist!$B$6:$B$102,"Setup and independence",Checklist!$G$6:$G$102,"Pass") | D5: =COUNTIFS(Checklist!$B$6:$B$102,"Setup and independence",Checklist!$G$6:$G$102,"Fail") | E5: =COUNTIFS(Checklist!$B$6:$B$102,"Setup and independence",Checklist!$G$6:$G$102,"N/A") | F5: =COUNTIFS(Checklist!$B$6:$B$102,"Setup and independence",Checklist!$G$6:$G$102,"Not started") | G5: =IF(B5=0,0,(C5+D5+E5)/B5)
A6: B. Re-run with date-stamped logs | B6: =COUNTIF(Checklist!$B$6:$B$102,"Re-run with date-stamped logs") | C6: =COUNTIFS(Checklist!$B$6:$B$102,"Re-run with date-stamped logs",Checklist!$G$6:$G$102,"Pass") | D6: =COUNTIFS(Checklist!$B$6:$B$102,"Re-run with date-stamped logs",Checklist!$G$6:$G$102,"Fail") | E6: =COUNTIFS(Checklist!$B$6:$B$102,"Re-run with date-stamped logs",Checklist!$G$6:$G$102,"N/A") | F6: =COUNTIFS(Checklist!$B$6:$B$102,"Re-run with date-stamped logs",Checklist!$G$6:$G$102,"Not started") | G6: =IF(B6=0,0,(C6+D6+E6)/B6)
A7: C. Code review: key assumptions | B7: =COUNTIF(Checklist!$B$6:$B$102,"Code review: key assumptions") | C7: =COUNTIFS(Checklist!$B$6:$B$102,"Code review: key assumptions",Checklist!$G$6:$G$102,"Pass") | D7: =COUNTIFS(Checklist!$B$6:$B$102,"Code review: key assumptions",Checklist!$G$6:$G$102,"Fail") | E7: =COUNTIFS(Checklist!$B$6:$B$102,"Code review: key assumptions",Checklist!$G$6:$G$102,"N/A") | F7: =COUNTIFS(Checklist!$B$6:$B$102,"Code review: key assumptions",Checklist!$G$6:$G$102,"Not started") | G7: =IF(B7=0,0,(C7+D7+E7)/B7)
A8: D. Results: represented correctly | B8: =COUNTIF(Checklist!$B$6:$B$102,"Results: represented correctly") | C8: =COUNTIFS(Checklist!$B$6:$B$102,"Results: represented correctly",Checklist!$G$6:$G$102,"Pass") | D8: =COUNTIFS(Checklist!$B$6:$B$102,"Results: represented correctly",Checklist!$G$6:$G$102,"Fail") | E8: =COUNTIFS(Checklist!$B$6:$B$102,"Results: represented correctly",Checklist!$G$6:$G$102,"N/A") | F8: =COUNTIFS(Checklist!$B$6:$B$102,"Results: represented correctly",Checklist!$G$6:$G$102,"Not started") | G8: =IF(B8=0,0,(C8+D8+E8)/B8)
A9: E. Tests and independent checks | B9: =COUNTIF(Checklist!$B$6:$B$102,"Tests and independent checks") | C9: =COUNTIFS(Checklist!$B$6:$B$102,"Tests and independent checks",Checklist!$G$6:$G$102,"Pass") | D9: =COUNTIFS(Checklist!$B$6:$B$102,"Tests and independent checks",Checklist!$G$6:$G$102,"Fail") | E9: =COUNTIFS(Checklist!$B$6:$B$102,"Tests and independent checks",Checklist!$G$6:$G$102,"N/A") | F9: =COUNTIFS(Checklist!$B$6:$B$102,"Tests and independent checks",Checklist!$G$6:$G$102,"Not started") | G9: =IF(B9=0,0,(C9+D9+E9)/B9)
A10: F. Data security and disclosure | B10: =COUNTIF(Checklist!$B$6:$B$102,"Data security and disclosure") | C10: =COUNTIFS(Checklist!$B$6:$B$102,"Data security and disclosure",Checklist!$G$6:$G$102,"Pass") | D10: =COUNTIFS(Checklist!$B$6:$B$102,"Data security and disclosure",Checklist!$G$6:$G$102,"Fail") | E10: =COUNTIFS(Checklist!$B$6:$B$102,"Data security and disclosure",Checklist!$G$6:$G$102,"N/A") | F10: =COUNTIFS(Checklist!$B$6:$B$102,"Data security and disclosure",Checklist!$G$6:$G$102,"Not started") | G10: =IF(B10=0,0,(C10+D10+E10)/B10)
A11: G. Documentation and reproducibility | B11: =COUNTIF(Checklist!$B$6:$B$102,"Documentation and reproducibility") | C11: =COUNTIFS(Checklist!$B$6:$B$102,"Documentation and reproducibility",Checklist!$G$6:$G$102,"Pass") | D11: =COUNTIFS(Checklist!$B$6:$B$102,"Documentation and reproducibility",Checklist!$G$6:$G$102,"Fail") | E11: =COUNTIFS(Checklist!$B$6:$B$102,"Documentation and reproducibility",Checklist!$G$6:$G$102,"N/A") | F11: =COUNTIFS(Checklist!$B$6:$B$102,"Documentation and reproducibility",Checklist!$G$6:$G$102,"Not started") | G11: =IF(B11=0,0,(C11+D11+E11)/B11)
A12: H. Close-out and sign-off | B12: =COUNTIF(Checklist!$B$6:$B$102,"Close-out and sign-off") | C12: =COUNTIFS(Checklist!$B$6:$B$102,"Close-out and sign-off",Checklist!$G$6:$G$102,"Pass") | D12: =COUNTIFS(Checklist!$B$6:$B$102,"Close-out and sign-off",Checklist!$G$6:$G$102,"Fail") | E12: =COUNTIFS(Checklist!$B$6:$B$102,"Close-out and sign-off",Checklist!$G$6:$G$102,"N/A") | F12: =COUNTIFS(Checklist!$B$6:$B$102,"Close-out and sign-off",Checklist!$G$6:$G$102,"Not started") | G12: =IF(B12=0,0,(C12+D12+E12)/B12)
A13: All sections | B13: =SUM(B5:B12) | C13: =SUM(C5:C12) | D13: =SUM(D5:D12) | E13: =SUM(E5:E12) | F13: =SUM(F5:F12) | G13: =IF(B13=0,0,(C13+D13+E13)/B13)
A15: Issues (rows whose ID contains EXAMPLE are not counted)
A16: Severity | B16: Total | C16: Open | D16: Resolved | E16: Accepted
A17: Critical | B17: =COUNTIFS('Issues log'!$D$5:$D$39,"Critical",'Issues log'!$A$5:$A$39,"<>*EXAMPLE*") | C17: =COUNTIFS('Issues log'!$D$5:$D$39,"Critical",'Issues log'!$H$5:$H$39,"Open",'Issues log'!$A$5:$A$39,"<>*EXAMPLE*") | D17: =COUNTIFS('Issues log'!$D$5:$D$39,"Critical",'Issues log'!$H$5:$H$39,"Resolved",'Issues log'!$A$5:$A$39,"<>*EXAMPLE*") | E17: =COUNTIFS('Issues log'!$D$5:$D$39,"Critical",'Issues log'!$H$5:$H$39,"Accepted",'Issues log'!$A$5:$A$39,"<>*EXAMPLE*")
A18: Major | B18: =COUNTIFS('Issues log'!$D$5:$D$39,"Major",'Issues log'!$A$5:$A$39,"<>*EXAMPLE*") | C18: =COUNTIFS('Issues log'!$D$5:$D$39,"Major",'Issues log'!$H$5:$H$39,"Open",'Issues log'!$A$5:$A$39,"<>*EXAMPLE*") | D18: =COUNTIFS('Issues log'!$D$5:$D$39,"Major",'Issues log'!$H$5:$H$39,"Resolved",'Issues log'!$A$5:$A$39,"<>*EXAMPLE*") | E18: =COUNTIFS('Issues log'!$D$5:$D$39,"Major",'Issues log'!$H$5:$H$39,"Accepted",'Issues log'!$A$5:$A$39,"<>*EXAMPLE*")
A19: Minor | B19: =COUNTIFS('Issues log'!$D$5:$D$39,"Minor",'Issues log'!$A$5:$A$39,"<>*EXAMPLE*") | C19: =COUNTIFS('Issues log'!$D$5:$D$39,"Minor",'Issues log'!$H$5:$H$39,"Open",'Issues log'!$A$5:$A$39,"<>*EXAMPLE*") | D19: =COUNTIFS('Issues log'!$D$5:$D$39,"Minor",'Issues log'!$H$5:$H$39,"Resolved",'Issues log'!$A$5:$A$39,"<>*EXAMPLE*") | E19: =COUNTIFS('Issues log'!$D$5:$D$39,"Minor",'Issues log'!$H$5:$H$39,"Accepted",'Issues log'!$A$5:$A$39,"<>*EXAMPLE*")
A20: Note | B20: =COUNTIFS('Issues log'!$D$5:$D$39,"Note",'Issues log'!$A$5:$A$39,"<>*EXAMPLE*") | C20: =COUNTIFS('Issues log'!$D$5:$D$39,"Note",'Issues log'!$H$5:$H$39,"Open",'Issues log'!$A$5:$A$39,"<>*EXAMPLE*") | D20: =COUNTIFS('Issues log'!$D$5:$D$39,"Note",'Issues log'!$H$5:$H$39,"Resolved",'Issues log'!$A$5:$A$39,"<>*EXAMPLE*") | E20: =COUNTIFS('Issues log'!$D$5:$D$39,"Note",'Issues log'!$H$5:$H$39,"Accepted",'Issues log'!$A$5:$A$39,"<>*EXAMPLE*")
A22: Fail rows without an Issue ID | B22: =COUNTIFS(Checklist!$G$6:$G$102,"Fail",Checklist!$K$6:$K$102,"")
A24: READY TO SIGN? | B24: =IF(AND(F13=0,C17=0,C18=0,B22=0),"YES: every task checked; no open Critical or Major issues","NOT YET: "&F13&" task(s) not started, "&(C17+C18)&" open Critical/Major issue(s), "&B22&" Fail row(s) without an Issue ID")
A25: A Fail row does not by itself block sign-off if its issue is Resolved or Accepted.

Sheet Reviewer
A1: Reviewer and environment
A2: Fill in every yellow cell. Copy computer and software details from environment.txt in your run folder.
A3: Item | B3: Your entry | C3: Guidance
A4: REVIEWER
A5: Full name | B5: Claude (Anthropic) — AI reviewer; findings to be confirmed by a human signatory
A6: Initials (used in the re-run folder name) | B6: Claude
A7: Title / role | B7: Independent reviewer (health economics / survey statistics)
A8: Organization | B8: Anthropic (Claude), engaged by the study author
A9: Email | B9: n/a
A10: Relationship to the study or its authors | B10: None. Did not write any code, data or text in the version reviewed. | C10: For example: none; colleague; co-author. Disclose any role in writing the code or text.
A11: Independent of the study's development? (Yes/No) | B11: Yes
A12: REVIEW
A13: Review start date (YYYY-MM-DD) | B13: 2026-10-21
A14: Review end date (YYYY-MM-DD) | B14: 2026-10-21
A15: Project version reviewed (Git commit ID, or ZIP download date) | B15: 33c6c47068df10f5f7cb56c8bf3c00cdd210a50d | C15: From environment.txt, 'Project version'
A16: How the project was obtained (Git clone / ZIP download) | B16: Git clone (depth 1) into an empty folder
A17: Re-run folder (qa/reruns/...) | B17: qa/Claude (collected by collect_rerun.py as qa/reruns/2026-10-21_CLAUDE and moved per the author's instruction) | C17: For example qa/reruns/2026-10-21_JD
A18: COMPUTER AND SOFTWARE (from environment.txt)
A19: Computer (make/model, or 'personal laptop', 'work desktop') | B19: Linux cloud VM (2 vCPU, 7.8 GB)
A20: Operating system and version | B20: Linux 6.18.44-fc-v139 x86_64, glibc 2.39
A21: Processor cores | B21: 2
A22: Memory (GB) | B22: 7.8
A23: Python version | B23: 3.13.16
A24: DuckDB version (must be 1.5.6) | B24: 1.5.6
A25: numpy / numba / pyarrow / scipy versions | B25: 2.5.4 / 0.68.0 / 26.0.0 / 1.18.1 (pandas 3.0.6, matplotlib 3.11.2, pytest 9.1.1)
A26: TOOLS USED FOR THE REVIEW
A27: Spreadsheet software (e.g., Microsoft Excel 365, version) | B27: openpyxl 3.x (workbook filled programmatically)
A28: Text editor or code viewer (e.g., VS Code, GitHub website) | B28: Direct file reads (Read tool) and ripgrep
A29: Terminal (e.g., PowerShell, macOS Terminal) | B29: bash
A30: PDF / Word viewer | B30: Markdown sources read directly; PDFs not opened
A31: Other tools (e.g., Git, R, calculator) | B31: git, Python/numpy/duckdb standalone verification scripts (review/scripts/), web search for citation verification

Sheet Checklist
A1: Checklist
A2: One row per task. Fill in the yellow columns. Fail rows need an Issue ID from the Issues log.
A4: ID | B4: Section | C4: Task | D4: How to check | E4: Where to look | F4: Expected result | G4: Status | H4: Date checked | I4: Initials | J4: Evidence (file, screenshot, or description) | K4: Issue ID | L4: Notes
A5: A. Setup and independence
A6: A1 | B6: Setup and independence | C6: Record who you are and your relationship to the study | D6: Fill in the Reviewer sheet. State whether you contributed to the study's code, data, or writing. | E6: Reviewer sheet | F6: Reviewer sheet complete; any relationship to the authors disclosed | G6: Pass | H6: 2026-10-21 | I6: Claude | J6: qa/Claude (see RERUN_SUMMARY.md, verification/, review/PEER_REVIEW.md) | L6: AI reviewer; a human signatory should countersign the attestation.
A7: A2 | B7: Setup and independence | C7: Use a fresh copy of the project | D7: Download the project from GitHub (ZIP or git clone) into a new, empty folder. Do not use the author's computer or an existing copy. | E7: start-here/README.md, step 3 | F7: A new project folder on your own computer | G7: Pass | H7: 2026-10-21 | I7: Claude | J7: qa/Claude (see RERUN_SUMMARY.md, verification/, review/PEER_REVIEW.md) | L7: git clone --depth 1 into an empty folder (scratchpad/repo).
A8: A3 | B8: Setup and independence | C8: Record the project version you are reviewing | D8: Git: run git rev-parse HEAD in the project folder. ZIP: record the download date and time. The re-run also records it in environment.txt ('Project version'). | E8: Reviewer sheet; start-here/logs/run_*/environment.txt | F8: Commit ID (or ZIP download date) recorded | G8: Pass | H8: 2026-10-21 | I8: Claude | J8: qa/Claude (see RERUN_SUMMARY.md, verification/, review/PEER_REVIEW.md) | L8: 33c6c47068df10f5f7cb56c8bf3c00cdd210a50d (merge of PR #28).
A9: A4 | B9: Setup and independence | C9: Install the software exactly as instructed | D9: Follow start-here/README.md steps 1 to 5 without changes. Note any step you had to change or that was unclear. | E9: start-here/README.md, steps 1-5 | F9: Setup ends with 'Successfully installed'; deviations noted | G9: Pass | H9: 2026-10-21 | I9: Claude | J9: qa/Claude (see RERUN_SUMMARY.md, verification/, review/PEER_REVIEW.md) | L9: Followed steps 1-5 as written; no deviations. One pip "new release available" notice.
A10: A5 | B10: Setup and independence | C10: Confirm the pinned DuckDB version | D10: Run .venv/bin/python -c "import duckdb; print(duckdb.__version__)" | E10: pyproject.toml; requirements.txt | F10: 1.5.6 (random draws depend on this version) | G10: Pass | H10: 2026-10-21 | I10: Claude | J10: qa/Claude (see RERUN_SUMMARY.md, verification/, review/PEER_REVIEW.md) | L10: 1.5.6
A11: B. Re-run with date-stamped logs
A12: B1 | B12: Re-run with date-stamped logs | C12: Run the quick trial | D12: Run .venv/bin/python start-here/run_all.py --quick and record the log folder name. | E12: start-here/logs/run_<date>_<time>_quick/ | F12: Ends with 'Your setup works.' | G12: Pass | H12: 2026-10-21 | I12: Claude | J12: qa/Claude (see RERUN_SUMMARY.md, verification/, review/PEER_REVIEW.md) | L12: logs/run_2026-10-21_145457_quick: ends "Your setup works." (2m 28s).
A13: B2 | B13: Re-run with date-stamped logs | C13: Start the full replication and record the start date and time | D13: Run .venv/bin/python start-here/run_all.py . Record the start time on the Run log sheet. | E13: start-here/logs/run_<date>_<time>/run_log.txt (first line) | F13: Run started; log folder created | G13: Pass | H13: 2026-10-21 | I13: Claude | J13: qa/Claude (see RERUN_SUMMARY.md, verification/, review/PEER_REVIEW.md) | L13: logs/run_2026-10-21_145729/run_log.txt first line 2026-10-21 14:57:29.
A14: B3 | B14: Re-run with date-stamped logs | C14: Stage 1 completed: populations built and calibration checks passed | D14: In run_log.txt, find 'Stage 1 finished'. Open each errors/output*/.../checks.json and confirm every check passes. | E14: run_log.txt; */errors/output*/*/checks.json | F14: Stage 1 finished; all calibration checks pass | G14: Pass | H14: 2026-10-21 | I14: Claude | J14: qa/Claude (see RERUN_SUMMARY.md, verification/, review/PEER_REVIEW.md) | L14: Stage 1 finished in 1m 17s. All checks.json entries pass (Part D entries marked "reported, not a target" are informational).
A15: B4 | B15: Re-run with date-stamped logs | C15: Stage 2 completed: reported estimates (parametric-rate bootstrap) | D15: Find 'Stage 2 finished' in run_log.txt. Record the time on the Run log sheet. | E15: run_log.txt; */estimation/results/ | F15: Stage 2 finished, no FAILED lines | G15: Pass | H15: 2026-10-21 | I15: Claude | J15: qa/Claude (see RERUN_SUMMARY.md, verification/, review/PEER_REVIEW.md) | L15: Stage 2 finished in 1h 05m 15s (published 1h 08m 24s).
A16: B5 | B16: Re-run with date-stamped logs | C16: Stage 3 completed: fixed-rate comparison | D16: Find 'Stage 3 finished' in run_log.txt. | E16: run_log.txt; */estimation/results_fixed/ | F16: Stage 3 finished, no FAILED lines | G16: Pass | H16: 2026-10-21 | I16: Claude | J16: qa/Claude (see RERUN_SUMMARY.md, verification/, review/PEER_REVIEW.md) | L16: Stage 3 finished in 1h 02m 59s in the resumed run (run_2026-10-21_165745).
A17: B6 | B17: Re-run with date-stamped logs | C17: Stage 4 completed: Part D pre-IRA reference | D17: Find 'Stage 4 finished' in run_log.txt. | E17: run_log.txt; part-d-ipm/pre-ira-reference.md | F17: Stage 4 finished, no FAILED lines | G17: Pass | H17: 2026-10-21 | I17: Claude | J17: qa/Claude (see RERUN_SUMMARY.md, verification/, review/PEER_REVIEW.md) | L17: Stage 4 finished in 58m 23s (run_2026-10-21_180449).
A18: B7 | B18: Re-run with date-stamped logs | C18: Stages 5 and 6 completed: report and manuscript tables | D18: Find 'Stage 5 finished' and 'Stage 6 finished' in run_log.txt. | E18: run_log.txt; shared/results/report/; manuscripts/generated/ | F18: Both stages finished | G18: Pass | H18: 2026-10-21 | I18: Claude | J18: qa/Claude (see RERUN_SUMMARY.md, verification/, review/PEER_REVIEW.md) | L18: Stages 5 and 6 finished (1s, 4s).
A19: B8 | B19: Re-run with date-stamped logs | C19: Stage 7 completed: automated tests pass | D19: Open the stage7 log. The last pytest line reports the number passed. | E19: start-here/logs/run_*/stage7_01_pytest.log | F19: All tests passed, 0 failed | G19: Pass | H19: 2026-10-21 | I19: Claude | J19: qa/Claude (see RERUN_SUMMARY.md, verification/, review/PEER_REVIEW.md) | L19: stage7_01_pytest.log: 38 passed in 59.00s.
A20: B9 | B20: Re-run with date-stamped logs | C20: Stage 8: the result check reproduces the published results | D20: Open the stage8 log (or verification/verify_check.txt after collecting). | E20: start-here/logs/run_*/stage8_01_start_here_verify.log | F20: REPRODUCED EXACTLY (or REPRODUCED, with the reason explained in Notes) | G20: Pass | H20: 2026-10-21 | I20: Claude | J20: qa/Claude (see RERUN_SUMMARY.md, verification/, review/PEER_REVIEW.md) | L20: REPRODUCED EXACTLY: 183 of 183 output files byte-for-byte identical.
A21: B10 | B21: Re-run with date-stamped logs | C21: If the run was interrupted, every stage still completed once | D21: If you resumed with --from, confirm that each stage 1-8 has a 'Stage N finished' line across the run folders. | E21: start-here/logs/run_*/run_log.txt | F21: Every stage finished at least once, in order; or N/A | G21: Pass | H21: 2026-10-21 | I21: Claude | J21: qa/Claude (see RERUN_SUMMARY.md, verification/, review/PEER_REVIEW.md) | L21: The first full run was stopped by the reviewer's own process time limit during stage 3 (CERT fixed-rate). Resumed with --only 3 then --from 4; every stage finished once, in order, across the three run folders.
A22: B11 | B22: Re-run with date-stamped logs | C22: The logs contain no errors | D22: Search every .log file for 'Traceback', 'Error', 'FAILED' and 'exit code: 1'. (A RuntimeWarning is not an error.) | E22: start-here/logs/run_*/*.log | F22: None found, or each explained in Notes | G22: Pass | H22: 2026-10-21 | I22: Claude | J22: qa/Claude (see RERUN_SUMMARY.md, verification/, review/PEER_REVIEW.md) | L22: No Traceback, FAILED or exit code: 1 in any .log.
A23: B12 | B23: Re-run with date-stamped logs | C23: Collect the re-run into the QA holding space | D23: Run .venv/bin/python qa/collect_rerun.py --reviewer "Your Name" --initials XX | E23: qa/reruns/<date>_<initials>/ | F23: Folder created; RERUN_SUMMARY.md lists your runs and the result check | G23: Pass | H23: 2026-10-21 | I23: Claude | J23: qa/Claude (see RERUN_SUMMARY.md, verification/, review/PEER_REVIEW.md) | L23: Collected as qa/reruns/2026-10-21_CLAUDE then moved to qa/Claude per the author's instruction.
... A25: B14 | B25: Re-run with date-stamped logs | C25: Review the file inventory | D25: Open file_inventory.csv in Excel. Filter matches_published for 'NO'. | E25: qa/reruns/<date>_<initials>/verification/file_inventory.csv | F25: No rows with 'NO', or each explained in Notes | G25: Pass | H25: 2026-10-21 | I25: Claude | J25: qa/Claude (see RERUN_SUMMARY.md, verification/, review/PEER_REVIEW.md) | L25: file_inventory.csv: 0 rows with NO.
A26: C. Code review: key assumptions
A27: C1 | B27: Code review: key assumptions | C27: Review is perfect: the audit finding equals the true error | D27: Confirm that the sampled units' y is read directly from the population's true y, with no review error or appeals. | E27: shared/sql/sample_srs.sql; shared/sql/sample_systematic.sql; */estimation/sql/*01_frame.sql | F27: Sample y = population y; no reviewer error modeled (manuscript Appendix B.6, item 1) | G27: Pass | H27: 2026-10-21 | I27: Claude | J27: qa/Claude (see RERUN_SUMMARY.md, verification/, review/PEER_REVIEW.md) | L27: sample_srs.sql / sample_systematic.sql read y from the population; no review error modeled.
A28: C2 | B28: Code review: key assumptions | C28: One audit per audit year; every method uses only that audit | D28: Confirm that expansion, ratio and regression read the same sample table, and that the bootstrap simulation uses only that year's audit findings (Part D: its own 5,000-PDE audit). | E28: */estimation/config.yaml (step order); shared/ipsim/simulation.py | F28: No method sees the population's true errors; Part D's two audits are as documented | G28: Pass | H28: 2026-10-21 | I28: Claude | J28: qa/Claude (see RERUN_SUMMARY.md, verification/, review/PEER_REVIEW.md) | L28: All analytic methods read the same sample table; simulation uses only that year's audit. Note README.md:14 wrongly describes a 108,000-beneficiary sample (I-08).
A29: C3 | B29: Code review: key assumptions | C29: Errors are independent of selection within a stratum | D29: Confirm that errors are fabricated before sampling and that sample selection uses only stratum and unit id (not y). | E29: */errors/sql/*apply_errors*.sql; shared/sql/sample_srs.sql; shared/sql/lib/00_rng.sql | F29: Selection keys never use y | G29: Pass | H29: 2026-10-21 | I29: Claude | J29: qa/Claude (see RERUN_SUMMARY.md, verification/, review/PEER_REVIEW.md) | L29: Selection keys use only seed/stream/stratum/unit id.
A30: C4 | B30: Code review: key assumptions | C30: Neyman allocation uses the population's stratum standard deviations | D30: Confirm n_h is proportional to N_h x S_h, with S_h computed from the population (standing in for prior-year data), and sums to the stated audit size. | E30: eipm/estimation/sql/01_frame.sql; perm-cert/estimation/sql/perm_01_frame.sql, cert_01_frame.sql; part-d-ipm/estimation/sql/40_simulation_inputs.sql; allocation.json | F30: Neyman formula; sizes 2,000 (EIPM), 520 per state (PERM), 37,651 (CERT), 5,000 PDEs (Part D) | G30: Pass | H30: 2026-10-21 | I30: Claude | J30: qa/Claude (see RERUN_SUMMARY.md, verification/, review/PEER_REVIEW.md) | L30: Neyman n_h ∝ N_h S_h with S_h from the population; sizes 2,000 / 520 / 37,651 / 5,000 confirmed. Part D lowest-decile stratum receives n_h ≈ 4.
A31: C5 | B31: Code review: key assumptions | C31: Netting: errors netted within the payment unit before measures | D31: Confirm over = sum max(y,0), under = sum max(-y,0), gross = over + under, net = over - under, after netting per enrollee/beneficiary/claim. | E31: */estimation/sql/*01_frame.sql; */errors/sql/*truth*.sql | F31: Matches manuscript Section 3.3 | G31: Pass | H31: 2026-10-21 | I31: Claude | J31: qa/Claude (see RERUN_SUMMARY.md, verification/, review/PEER_REVIEW.md) | L31: Netting as stated in the population and analytic estimators.
A32: C6 | B32: Code review: key assumptions | C32: Unknown payments (e.g., missing documentation) count as improper | D32: Confirm missing-documentation errors set the whole payment (or every HCC) to improper. | E32: part-c-ipm/errors/sql/04_apply_errors.sql; perm-cert/errors/sql/cert_02_apply_errors.sql | F32: Follows CMS practice (Appendix B.6, item 6) | G32: Pass | H32: 2026-10-21 | I32: Claude | J32: qa/Claude (see RERUN_SUMMARY.md, verification/, review/PEER_REVIEW.md) | L32: Missing documentation loses every HCC (Part C); no/insufficient documentation = whole claim (CERT).
A33: C7 | B33: Code review: key assumptions | C33: Calibration is one closed-form multiplier, with no iterative tuning | D33: Confirm each calibrated rate = base probability x (target dollars / expected dollars), and that the multiplier is logged. | E33: */errors/sql/*apply_errors*.sql; part-d-ipm/errors/sql/03_init_calibration.sql; truth.json (by.calibration) | F33: One multiplier per target; recorded in truth.json | G33: Pass | H33: 2026-10-21 | I33: Claude | J33: qa/Claude (see RERUN_SUMMARY.md, verification/, review/PEER_REVIEW.md) | L33: One closed-form multiplier per target; logged in truth.json.
A34: C8 | B34: Code review: key assumptions | C34: Random draws are deterministic functions of (seed, stream, key) | D34: Confirm SQL draws hash a single string per stream and simulation draws use PCG64 seeded by SeedSequence([scenario seed, audit year]). | E34: shared/sql/lib/00_rng.sql; shared/ipsim/engine.py (child_seed); shared/ipsim/simulation.py | F34: No unseeded randomness anywhere | G34: Pass | H34: 2026-10-21 | I34: Claude | J34: qa/Claude (see RERUN_SUMMARY.md, verification/, review/PEER_REVIEW.md) | L34: hash(seed,stream,key) in SQL; PCG64 via SeedSequence([seed, audit year]) in simulation.
A35: C9 | B35: Code review: key assumptions | C35: Scale factors convert synthetic units to national dollars | D35: Confirm w_pop: Part C 100, Part D 500, EIPM 100, PERM 200, CERT 200; national dollars = rate x total payments x w_pop. | E35: */errors/config.yaml (w_pop); shared/sql/report.sql | F35: Values as stated; rates are scale-free | G35: Pass | H35: 2026-10-21 | I35: Claude | J35: qa/Claude (see RERUN_SUMMARY.md, verification/, review/PEER_REVIEW.md) | L35: w_pop 100/500/100/200/200 in configs; report.sql duplicates the values (agree).
A36: C10 | B36: Code review: key assumptions | C36: Analytic intervals: normal (1.96) with finite population correction | D36: Confirm expansion and ratio variances use the stratified SRS formula with (1 - n_h/N_h), and intervals are estimate +/- 1.96 SE. | E36: shared/sql/lib/02_estimators.sql (ipm_expansion, ipm_ratio) | F36: Matches manuscript Section 3.4 | G36: Pass | H36: 2026-10-21 | I36: Claude | J36: qa/Claude (see RERUN_SUMMARY.md, verification/, review/PEER_REVIEW.md) | L36: Verified against an independent per-unit numpy reference and against the exact design SE from the population (Part C ratio 54.65 vs 54.85 bp).
A37: C11 | B37: Code review: key assumptions | C37: Regression: models fit within strata; residual t interval | D37: Confirm design-weighted least squares within each model stratum, T = sum of predictions + weighted residuals, variance from residuals, t with df = n - strata - terms. | E37: shared/ipsim/regression.py; */estimation/sql/*30_regression.sql | F37: Matches manuscript Section 3.4 | G37: Fail | H37: 2026-10-21 | I37: Claude | J37: qa/Claude (see RERUN_SUMMARY.md, verification/, review/PEER_REVIEW.md) | K37: I-07 | L37: df subtracts intercepts twice (regression.py:110); negligible at n=990
A38: C12 | B38: Code review: key assumptions | C38: Regression fallback: intercept-only with too few errors | D38: Confirm a stratum uses an intercept-only model when it has fewer than 10 audited errors or fewer than (terms + 5) units. | E38: shared/ipsim/regression.py; */estimation/config.yaml (reg_min_errors: 10) | F38: Threshold 10 errors; terms + 5 units | G38: Fail | H38: 2026-10-21 | I38: Claude | J38: qa/Claude (see RERUN_SUMMARY.md, verification/, review/PEER_REVIEW.md) | K38: I-07 | L38: fallback counts audited errors in any domain, not the domain estimated (regression.py:82)
A39: C13 | B39: Code review: key assumptions | C39: Regression predictors by program | D39: Confirm reg_predictors: Part C x, demo_score, months, n_hcc; Part D x, gdc_sub, n_pde, catastrophic (post-strata LTC/LIS/other); EIPM x, age, hh_size, fpl_pct, months; PERM x, month, bene_n_pay, bene_paid; CERT x. | E39: */estimation/config.yaml; perm-cert/estimation/perm.yaml, cert.yaml | F39: Predictors as listed in manuscript Section 3.4 | G39: Pass | H39: 2026-10-21 | I39: Claude | J39: qa/Claude (see RERUN_SUMMARY.md, verification/, review/PEER_REVIEW.md) | L39: Predictors as listed.
A40: C14 | B40: Code review: key assumptions | C40: Bootstrap simulation (fixed rates): p = f/n, q = g/f per donor kind | D40: Confirm each non-audited unit is in error with p_k, partial with q_k, partial size drawn uniformly from the audited partial sizes. | E40: shared/ipsim/simulation.py; */estimation/*simulation.py; */estimation/sql/*40_simulation_inputs.sql | F40: Matches manuscript Section 3.5 | G40: Fail | H40: 2026-10-21 | I40: Claude | J40: qa/Claude (see RERUN_SUMMARY.md, verification/, review/PEER_REVIEW.md) | K40: I-10 | L40: Part C kernel uses the HCC mean audited loss, not a uniform draw from the partial list (simulation.py:104,133); §3.5/A.5 say "drawn uniformly"
A41: C15 | B41: Code review: key assumptions | C41: Bootstrap simulation (parametric rates): binomial redraw each iteration | D41: Confirm p~ = Binomial(n, p)/n and q~ = Binomial(f, q)/f before every iteration, and that zero-failure rates stay at zero. | E41: shared/ipsim/simulation.py (sim_rates: parametric) | F41: Matches manuscript Section 3.6 | G41: Fail | H41: 2026-10-21 | I41: Claude | J41: qa/Claude (see RERUN_SUMMARY.md, verification/, review/PEER_REVIEW.md) | K41: I-06 | L41: q~ is drawn as Binomial(f, q)/f with the observed f rather than the redrawn f~ (part-d simulation.py:204; perm_simulation.py:94; cert_simulation.py:197). Zero-failure rates stay at zero: confirmed.
A42: C16 | B42: Code review: key assumptions | C42: Audited units keep their own findings | D42: Confirm the simulation assigns errors only to non-audited units and keeps each audited unit's actual finding. | E42: */estimation/*simulation.py | F42: Audited units unchanged across iterations | G42: Fail | H42: 2026-10-21 | I42: Claude | J42: qa/Claude (see RERUN_SUMMARY.md, verification/, review/PEER_REVIEW.md) | K42: I-02 | L42: Audited units keep findings (confirmed), but non-audited Part C recipients receive additions independently of failures and the two are netted; the population never co-generates them (04_apply_errors.sql:125). Simulated under runs ~8% low.
A43: C17 | B43: Code review: key assumptions | C43: Simulation estimate and interval: mean and 2.5th-97.5th percentiles of 1,000 iterations | D43: Confirm sim_iterations: 1000 and the percentile interval. | E43: shared/ipsim/simulation.py; */estimation/config.yaml | F43: 1,000 iterations; mean; 2.5th and 97.5th percentiles | G43: Pass | H43: 2026-10-21 | I43: Claude | J43: qa/Claude (see RERUN_SUMMARY.md, verification/, review/PEER_REVIEW.md) | L43: 1,000 iterations; mean; 2.5/97.5 percentiles (linear interpolation).
A44: C18 | B44: Code review: key assumptions | C44: Scoring: coverage, 25 audit years, medians | D44: Confirm an interval covers if lower <= truth <= upper, undefined intervals count as not covering, and the report uses audit years 1-25 with medians. | E44: shared/sql/lib/02_estimators.sql (ipm_score); shared/sql/report.sql; shared/report.yaml (audit_years: 25) | F44: As stated in the README and manuscript Section 3.7 | G44: Pass | H44: 2026-10-21 | I44: Claude | J44: qa/Claude (see RERUN_SUMMARY.md, verification/, review/PEER_REVIEW.md) | L44: As stated. mc_se_coverage uses the observed p and reads 0 at 25/25 (I-15).
A45: C19 | B45: Code review: key assumptions | C45: Part C: population size, payment total and HCC model | D45: Confirm about 330,000 enrollees (x100), 550 contracts, payment scaled to $388.72B, HCC hierarchies (severe/mild within 10 illustrative families). | E45: part-c-ipm/errors/config.yaml; part-c-ipm/errors/sql/01-03*.sql | F45: Matches Appendix B.1 | G45: Pass | H45: 2026-10-21 | I45: Claude | J45: qa/Claude (see RERUN_SUMMARY.md, verification/, review/PEER_REVIEW.md) | L45: Matches B.1.
A46: C20 | B46: Code review: key assumptions | C46: Part C: error mechanisms and calibration targets | D46: Confirm unsupported HCCs (deleted or moved down), missing documentation, and supported-but-not-coded HCCs (underpayments); targets 5.29% unsupported, 0.22% missing documentation, 0.57% underpayments. | E46: part-c-ipm/errors/config.yaml (target_*); part-c-ipm/errors/sql/04_apply_errors.sql | F46: FY 2025 Part C: 6.09% gross, $21.43B over, $2.23B under | G46: Pass | H46: 2026-10-21 | I46: Claude | J46: qa/Claude (see RERUN_SUMMARY.md, verification/, review/PEER_REVIEW.md) | L46: Targets and mechanisms as stated; checks pass (6.06% vs 6.09%).
A47: C21 | B47: Code review: key assumptions | C47: Part C: audit design (990 enrollees, 330 per risk-score tercile) | D47: Confirm the estimation allocation. NOTE: the design block in part-c-ipm/errors/config.yaml lists 1,500 per stratum; confirm it is description only and not used by the estimation. | E47: part-c-ipm/estimation/config.yaml (allocation); part-c-ipm/errors/config.yaml (design) | F47: 330 x 3 used; record the design-block discrepancy as an issue (Minor) | G47: Fail | H47: 2026-10-21 | I47: Claude | J47: qa/Claude (see RERUN_SUMMARY.md, verification/, review/PEER_REVIEW.md) | K47: I-01 | L47: Confirmed: errors/config.yaml design block lists 1,500 per stratum; estimation uses 330 x 3 = 990. Metadata only.
A48: C22 | B48: Code review: key assumptions | C48: Part C: expansion in risk-score units; simulation donors are HCCs | D48: Confirm expansion = mean risk-score error x tercile size x national mean county rate x months; simulation uses 20 HCC failure rates and 10 family addition rates, never extrapolating to unaudited HCCs. | E48: part-c-ipm/estimation/sql/10_expansion.sql; part-c-ipm/estimation/simulation.py; sql/40_simulation_inputs.sql | F48: Matches Appendix B.1 | G48: Fail | H48: 2026-10-21 | I48: Claude | J48: qa/Claude (see RERUN_SUMMARY.md, verification/, review/PEER_REVIEW.md) | K48: I-10 | L48: Expansion and donor structure as described. Note B.1 says mean loss (correct) while §3.5/§3.6/A.5 say uniform draw; §5.3 says two draws per stratum (Part C: 30 draws per iteration).
A49: C23 | B49: Code review: key assumptions | C49: Part D: post-IRA CY 2025 benefit parameters | D49: Confirm $590 deductible, $2,000 out-of-pocket threshold, 25% initial coinsurance, manufacturer 10%/20% (brand), reinsurance 20% brand/40% generic, LIS copays $4.90/$12.15. | E49: part-d-ipm/errors/config.yaml; part-d-ipm/errors/sql/05_benefit.sql | F49: Matches Appendix B.2 and CMS CY 2025 parameters | G49: Pass | H49: 2026-10-21 | I49: Claude | J49: qa/Claude (see RERUN_SUMMARY.md, verification/, review/PEER_REVIEW.md) | L49: All CY 2025 parameters correct. Simplifications not stated: all LIS pay $4.90/$12.15; MDP affects plan liability only (I-11).
A50: C24 | B50: Code review: key assumptions | C50: Part D: error rates and sizes (not calibrated) | D50: Confirm 10% of LTC PDEs and 2.5% of other PDEs in error; 90% full (GDC to 0), 10% partial uniform on [-100%, 100%). Truth 1.38% (published FY 2025 rate 4.00% is intentionally not targeted). | E50: part-d-ipm/errors/config.yaml; part-d-ipm/errors/sql/02_candidate_errors.sql, 04_apply_errors.sql | F50: Matches Appendix B.2 | G50: Pass | H50: 2026-10-21 | I50: Claude | J50: qa/Claude (see RERUN_SUMMARY.md, verification/, review/PEER_REVIEW.md) | L50: As stated.
A51: C25 | B51: Code review: key assumptions | C51: Part D: numpy payment function reproduces the SQL benefit to the cent | D51: Confirm the test exists and passed in stage 7. | E51: shared/tests/test_simulation.py; part-d-ipm/estimation/simulation.py | F51: Test present and passing | G51: Pass | H51: 2026-10-21 | I51: Claude | J51: qa/Claude (see RERUN_SUMMARY.md, verification/, review/PEER_REVIEW.md) | L51: Present and passing.
A52: C26 | B52: Code review: key assumptions | C52: Part D: two audits and the expansion delta-method interval | D52: Confirm the 990-beneficiary SRS (ratio, regression) and the 5,000-PDE Neyman audit in 3 strata (expansion, simulation); expansion interval moves each stratum rate +/-1 SE and reruns the benefit. | E52: part-d-ipm/estimation/config.yaml; sql/40_simulation_inputs.sql; simulation.py (run_expansion) | F52: Matches Appendix B.2 | G52: Fail | H52: 2026-10-21 | I52: Claude | J52: qa/Claude (see RERUN_SUMMARY.md, verification/, review/PEER_REVIEW.md) | K52: I-05 | L52: Two audits as documented (990 SRS; 5,000 PDE Neyman, 3 strata). The 990-beneficiary audit reviews every PDE (~41,000 PDEs), and the PDE-audit expansion is a uniform-haircut plug-in (simulation.py:228) whose delta-method SE understates its own SD (0.37 vs 0.54 pts).
A53: C27 | B53: Code review: key assumptions | C53: Part D pre-IRA: CY 2023 benefit parameters | D53: Confirm $505 deductible, $4,660 initial coverage limit, $7,400 TrOOP threshold, 70% coverage-gap discount, 80% catastrophic reinsurance, LIS copays $4.15/$10.35. | E53: part-d-ipm/errors/pre_ira.yaml; part-d-ipm/errors/sql/05_benefit_pre_ira.sql | F53: Matches part-d-ipm/pre-ira-reference.md | G53: Pass | H53: 2026-10-21 | I53: Claude | J53: qa/Claude (see RERUN_SUMMARY.md, verification/, review/PEER_REVIEW.md) | L53: Matches pre-ira-reference.md.
A54: C28 | B54: Code review: key assumptions | C54: PERM: states, error rates and federal share | D54: Confirm 9 states with eligibility rates on a 2.00%-4.00% grid; FFS claims errors 6.5% (70% all-or-nothing, 30% partial), MC 0.3%; rates at federal share (sum y x FMAP / sum x x FMAP). | E54: perm-cert/errors/perm.yaml; perm-cert/errors/sql/perm_02*.sql, perm_03*.sql | F54: Matches Appendix B.3; pooled about 6.12% | G54: Pass | H54: 2026-10-21 | I54: Claude | J54: qa/Claude (see RERUN_SUMMARY.md, verification/, review/PEER_REVIEW.md) | L54: Matches B.3; pooled 6.09%.
A55: C29 | B55: Code review: key assumptions | C55: PERM: gross combines eligibility and claims errors without double counting | D55: Confirm gross = whole payment if the beneficiary is ineligible, otherwise the claims error. | E55: perm-cert/errors/sql/perm_04_truth.sql | F55: Claims + eligibility - overlap | G55: Pass | H55: 2026-10-21 | I55: Claude | J55: qa/Claude (see RERUN_SUMMARY.md, verification/, review/PEER_REVIEW.md) | L55: Gross = whole payment if ineligible, else claims error.
A56: C30 | B56: Code review: key assumptions | C56: PERM: audit design and national pooling | D56: Confirm 520 payments per state, 10 strata (payment type x 5 quintiles), Neyman, systematic selection after sorting by amount; national pooling adds dollars and variances (analytic) and sums iteration totals (simulation). | E56: perm-cert/estimation/perm.yaml; shared/sql/sample_systematic.sql; perm-cert/estimation/sql/perm_95_national.sql | F56: Matches Appendix B.3 | G56: Fail | H56: 2026-10-21 | I56: Claude | J56: qa/Claude (see RERUN_SUMMARY.md, verification/, review/PEER_REVIEW.md) | K56: I-09 | L56: Code matches Appendix B.3 (520, 10 strata type x quintile, Neyman, systematic, national pooling correct). perm-cert/README.md:17, perm.yaml:46 and data_dictionary.md:110 describe quarter x equal-dollar strata instead. Also I-18: eligibility is a whole-year attribute propagated to all of a beneficiary's payments.
A57: C31 | B57: Code review: key assumptions | C57: EIPM: overpayments only; technical and monetary errors | D57: Confirm no underpayments; technical errors (whole APTC) are 48% of improper dollars; monetary errors raise supported income by a lognormal factor and recompute APTC; target 0.89%. | E57: eipm/errors/config.yaml; eipm/errors/sql/02_apply_errors.sql | F57: Matches Appendix B.4 | G57: Pass | H57: 2026-10-21 | I57: Claude | J57: qa/Claude (see RERUN_SUMMARY.md, verification/, review/PEER_REVIEW.md) | L57: Matches B.4.
A58: C32 | B58: Code review: key assumptions | C58: EIPM: APTC schedule and simulation income clipping | D58: Confirm the enhanced applicable-percentage schedule (0% to 8.5%) and that simulated incomes are clipped to 100-600% FPL. | E58: eipm/errors/config.yaml (applicable_schedule); eipm/estimation/simulation.py | F58: As stated | G58: Pass | H58: 2026-10-21 | I58: Claude | J58: qa/Claude (see RERUN_SUMMARY.md, verification/, review/PEER_REVIEW.md) | L58: Schedule and 100-600% FPL clipping confirmed.
A59: C33 | B59: Code review: key assumptions | C59: EIPM: audit design | D59: Confirm stratified SRS of 2,000 applications, Neyman over 5 APTC quintiles (illustrative strata). | E59: eipm/estimation/config.yaml; eipm/estimation/sql/01_frame.sql | F59: Matches Appendix B.4 | G59: Pass | H59: 2026-10-21 | I59: Claude | J59: qa/Claude (see RERUN_SUMMARY.md, verification/, review/PEER_REVIEW.md) | L59: Matches B.4.
A60: C34 | B60: Code review: key assumptions | C60: CERT: claim types and payments | D60: Confirm 4 claim types (IPPS 40,000; Part A other 900,000; Part B 4,000,000; DMEPOS 400,000 synthetic claims) scaled to $118.5B, $197.9B, $114.1B, $9.4B ($439.9B). | E60: perm-cert/errors/cert.yaml; perm-cert/errors/sql/cert_01_population.sql | F60: Matches Appendix B.5 | G60: Pass | H60: 2026-10-21 | I60: Claude | J60: qa/Claude (see RERUN_SUMMARY.md, verification/, review/PEER_REVIEW.md) | L60: Matches B.5.
A61: C35 | B61: Code review: key assumptions | C61: CERT: error mix and calibration | D61: Confirm whole-claim overpayments 92% of overpayment dollars, partial 8% (5-60% of payment), underpayments 5-50%; per-type closed-form rates from FY 2025 dollars. | E61: perm-cert/errors/cert.yaml; perm-cert/errors/sql/cert_02_apply_errors.sql | F61: Truth 6.50% gross (published 6.55%); $0.92B under | G61: Pass | H61: 2026-10-21 | I61: Claude | J61: qa/Claude (see RERUN_SUMMARY.md, verification/, review/PEER_REVIEW.md) | L61: Checks pass: 6.50% vs 6.55%; $0.92B under.
A62: C36 | B62: Code review: key assumptions | C62: CERT: audit design | D62: Confirm 37,651 claims (IPPS 8,750; Part A other 8,651; Part B 11,600; DMEPOS 8,650), Neyman across 5 payment quintiles within type; no MAC jurisdictions; no A-to-B rebilling. | E62: perm-cert/estimation/cert.yaml; sql/cert_01_frame.sql, cert_02_sample.sql | F62: Matches Appendix B.5 | G62: Pass | H62: 2026-10-21 | I62: Claude | J62: qa/Claude (see RERUN_SUMMARY.md, verification/, review/PEER_REVIEW.md) | L62: Matches B.5.
A63: C37 | B63: Code review: key assumptions | C63: Audit-size projection formula | D63: Confirm the share of the current audit = (parametric half-width / analytic half-width) squared. | E63: manuscripts/scripts/build_tables.py | F63: Matches manuscript Sections 3.7 and 5.2 | G63: Fail | H63: 2026-10-21 | I63: Claude | J63: qa/Claude (see RERUN_SUMMARY.md, verification/, review/PEER_REVIEW.md) | K63: I-03 | L63: Formula implemented as stated (build_tables.py). The inputs are questionable: the parametric half-width appears ~7-10% below the simulation estimator's true SD in Part C and EIPM, so the projected shares (79%, 80%) are understated.
A64: D. Results: represented correctly
A65: D1 | B65: Results: represented correctly | C65: Main README: gross improper payments (dollars) table | D65: For each program and method, compare True / Estimated / Upper / Lower with by_scenario.csv (domain ending in 'gross'; PERM and CERT 'national' rows): true_improper_usd, median_estimate_usd, median_upper_usd, median_lower_usd. | E65: README.md (Results); shared/results/report/by_scenario.csv | F65: Every value matches after rounding to $0.01B | G65: Pass | H65: 2026-10-21 | I65: Claude | J65: qa/Claude (see RERUN_SUMMARY.md, verification/, review/PEER_REVIEW.md) | L65: All 20 rows match by_scenario.csv after rounding.
A66: D2 | B66: Results: represented correctly | C66: Main README: gross improper payment rates table | D66: Same comparison using true_rate, median_estimate, median_upper, median_lower. | E66: README.md (Results); shared/results/report/by_scenario.csv | F66: Every value matches after rounding to 0.01% | G66: Pass | H66: 2026-10-21 | I66: Claude | J66: qa/Claude (see RERUN_SUMMARY.md, verification/, review/PEER_REVIEW.md) | L66: All 20 rows match.
A67: D3 | B67: Results: represented correctly | C67: Main README: Findings and recommendations numbers | D67: Check 121/125 (96.8%), 111/125, 108/125, 30/125, 11-21% narrower, 63%, 1.5-6.6% and 16.6% MAE, 19-20 of 25, 15 of 25, and 20-38% smaller audits against the tables. | E67: README.md (Findings); manuscripts/generated/tables.md; results_long.csv | F67: Every number traceable to a table | G67: Pass | H67: 2026-10-21 | I67: Claude | J67: qa/Claude (see RERUN_SUMMARY.md, verification/, review/PEER_REVIEW.md) | L67: Every number traceable (121/125, 30/125, 111, 108, width ratios 89/89/79/79/37%, audit shares 79/80/63/62%, MAE 1.5-6.6% and 16.6%).
A68: D4 | B68: Results: represented correctly | C68: Program READMEs: results tables | D68: For each program README, compare the Dollars, Rates and coverage tables with by_scenario.csv. | E68: part-c-ipm, part-d-ipm, eipm, perm-cert README.md; by_scenario.csv | F68: All values match | G68: Pass | H68: 2026-10-21 | I68: Claude | J68: qa/Claude (see RERUN_SUMMARY.md, verification/, review/PEER_REVIEW.md) | L68: Program README tables match by_scenario.csv.
A69: D5 | B69: Results: represented correctly | C69: Manuscript tables match the generated tables | D69: Compare Tables 2, 3, 4, 5 and C1 in manuscript.pdf with tables.md. | E69: manuscripts/manuscript.pdf; manuscripts/generated/tables.md | F69: Identical | G69: Pass | H69: 2026-10-21 | I69: Claude | J69: qa/Claude (see RERUN_SUMMARY.md, verification/, review/PEER_REVIEW.md) | L69: manuscript.md tables are assembled from tables.md (identical after re-run).
A70: D6 | B70: Results: represented correctly | C70: Manuscript text numbers match the tables | D70: Check every number in the abstract, Results (Section 4) and Discussion (Section 5) against Tables 2-5. | E70: manuscripts/sections/*.md; manuscripts/generated/tables.md | F70: Every number traceable; none contradicts a table | G70: Pass | H70: 2026-10-21 | I70: Claude | J70: qa/Claude (see RERUN_SUMMARY.md, verification/, review/PEER_REVIEW.md) | L70: Every number in the abstract, §4 and §5 traces to Tables 2-5 / results_long.csv.
A71: D7 | B71: Results: represented correctly | C71: Manuscript Table 1 (populations) matches the configs and truth files | D71: Compare unit counts, audit sizes and true gross rates with the configs and truth.json. | E71: manuscripts/sections/01_background_methods.md; */errors/output*/*/truth.json | F71: All match | G71: Pass | H71: 2026-10-21 | I71: Claude | J71: qa/Claude (see RERUN_SUMMARY.md, verification/, review/PEER_REVIEW.md) | L71: Unit counts, audit sizes and true rates match configs and truth.json.
A72: D8 | B72: Results: represented correctly | C72: Figures 1 and 2 show the values in results_long.csv | D72: Spot-check at least 3 bars in each figure against results_long.csv. | E72: manuscripts/generated/fig1_width.png, fig2_coverage.png; results_long.csv | F72: Bars match the table values | G72: Pass | H72: 2026-10-21 | I72: Claude | J72: qa/Claude (see RERUN_SUMMARY.md, verification/, review/PEER_REVIEW.md) | L72: Figures regenerated identically; values match results_long.csv.
A73: D9 | B73: Results: represented correctly | C73: One-pager and conference abstract numbers | D73: Check every number against the manuscript tables; confirm the abstract is 500 words or fewer. | E73: manuscripts/one-pager.md; manuscripts/conference-abstract.md | F73: All match | G73: Pass | H73: 2026-10-21 | I73: Claude | J73: qa/Claude (see RERUN_SUMMARY.md, verification/, review/PEER_REVIEW.md) | L73: All numbers match; abstract 511 words incl. headings (body under 500).
A74: D10 | B74: Results: represented correctly | C74: Calibration targets match public sources | D74: Check the FY 2025 public figures used as targets (Part C 6.09%, $21.43B/$2.23B; Medicaid 6.12%; EIPM 0.89% with 0.43 technical; CERT 6.55% and claim-type figures; Part D 4.00%) against the cited CMS sources. | E74: manuscript Section 3.2 and Appendix B; literature review Section 3 links | F74: Each target matches its public source | G74: Pass | H74: 2026-10-21 | I74: Claude | J74: qa/Claude (see RERUN_SUMMARY.md, verification/, review/PEER_REVIEW.md) | L74: All FY 2025 figures match the CMS fact sheet, Part C/D findings documents, Supplemental Improper Payment Data and the EIPM findings page.
A75: D11 | B75: Results: represented correctly | C75: True values in the tables equal the truth files | D75: Confirm true_rate in by_scenario.csv equals theta in each estimation truth.json and the populations' truth.json. | E75: by_scenario.csv; */estimation/results/*/truth.json; */errors/output*/*/truth.json | F75: Identical | G75: Pass | H75: 2026-10-21 | I75: Claude | J75: qa/Claude (see RERUN_SUMMARY.md, verification/, review/PEER_REVIEW.md) | L75: Identical.
A76: D12 | B76: Results: represented correctly | C76: Hand-check one median and one coverage count | D76: Open by_audit_year.csv (or .parquet). Filter Part C, national|gross, simulation. Compute the median of the 25 estimates and count truth_in_ci = 'inside'. | E76: shared/results/report/by_audit_year.csv | F76: Median equals median_estimate; count equals n_truth_inside (24) | G76: Pass | H76: 2026-10-21 | I76: Claude | J76: qa/Claude (see RERUN_SUMMARY.md, verification/, review/PEER_REVIEW.md) | L76: Part C national|gross simulation: median 6.08%, 24 of 25 inside (computed from by_audit_year.parquet).
A77: D13 | B77: Results: represented correctly | C77: Part D pre-IRA reference is stated as reference only | D77: Confirm pre-ira-reference.md says it is not part of the reported results and that README tables use post-IRA results. | E77: part-d-ipm/pre-ira-reference.md; README.md | F77: Clearly labeled as a robustness reference | G77: Pass | H77: 2026-10-21 | I77: Claude | J77: qa/Claude (see RERUN_SUMMARY.md, verification/, review/PEER_REVIEW.md) | L77: Clearly labeled as reference only.
A78: D14 | B78: Results: represented correctly | C78: Conclusions are supported by the results | D78: Read the Conclusions and Recommendations. Confirm each claim (validity, accuracy, precision, audit-size reduction 'pending confirmation') is supported and its limits are stated. | E78: README.md; manuscript Sections 5-7 | F78: No claim goes beyond the evidence | G78: Fail | H78: 2026-10-21 | I78: Claude | J78: qa/Claude (see RERUN_SUMMARY.md, verification/, review/PEER_REVIEW.md) | K78: I-03 | L78: Validity and point accuracy supported. "Narrower" and "20-38% smaller audits" are not yet supported: see I-03 (SE understatement), I-04 (model-dependent gain), I-05 (Part D comparator), I-14 (25 audit years). Abstract and Conclusion state them without the Discussion's hedging.
A79: D15 | B79: Results: represented correctly | C79: Limitations are complete | D79: Confirm the limitations cover 25 audit years (Monte Carlo SE about 4.4 points), synthetic populations, perfect review, Part D design differences, fixed error sizes, and one-sided recovery bounds untested. | E79: manuscript Section 5.4 | F79: All present | G79: Fail | H79: 2026-10-21 | I79: Claude | J79: qa/Claude (see RERUN_SUMMARY.md, verification/, review/PEER_REVIEW.md) | K79: I-11 | L79: Listed limitations present. Missing: error probability independent of payment size within strata is assumed in Part C and Part D too (B.6.3 names only PERM, CERT, EIPM); Part D strata and audit sizes are not public (§3.2 omits Part D).
A80: E. Tests and independent checks
A81: E1 | B81: Tests and independent checks | C81: Automated tests pass on your computer | D81: Run .venv/bin/python -m pytest -q shared/tests (also run in stage 7). | E81: shared/tests/ | F81: All passed | G81: Pass | H81: 2026-10-21 | I81: Claude | J81: qa/Claude (see RERUN_SUMMARY.md, verification/, review/PEER_REVIEW.md) | L81: 38 passed.
A82: E2 | B82: Tests and independent checks | C82: Results do not depend on the number of processor threads | D82: Run .venv/bin/python -m ipsim eipm/estimation/config.yaml --out qa/tmp_threads1 --threads 1 . Compare qa/tmp_threads1/base/manifest.json with eipm/estimation/results/base/manifest.json (estimates.parquet sha256). Then delete qa/tmp_threads1. | E82: eipm/estimation/results/base/manifest.json | F82: Identical sha256 fingerprints | G82: Pass | H82: 2026-10-21 | I82: Claude | J82: qa/Claude (see RERUN_SUMMARY.md, verification/, review/PEER_REVIEW.md) | L82: EIPM --threads 1: all five manifest sha256 values identical.
A83: E3 | B83: Tests and independent checks | C83: Census check: auditing every unit returns the true rate | D83: Confirm the test exists and passed. | E83: shared/tests/test_simulation.py | F83: Test present and passing | G83: Pass | H83: 2026-10-21 | I83: Claude | J83: qa/Claude (see RERUN_SUMMARY.md, verification/, review/PEER_REVIEW.md) | L83: Present and passing.
A84: E4 | B84: Tests and independent checks | C84: Estimators match an independent implementation | D84: Confirm the SQL estimators are tested against a separate numpy implementation. | E84: shared/tests/test_estimators.py | F84: Test present and passing | G84: Pass | H84: 2026-10-21 | I84: Claude | J84: qa/Claude (see RERUN_SUMMARY.md, verification/, review/PEER_REVIEW.md) | L84: Present and passing (shared macros; the Part C and Part D expansions are not covered).
A85: E5 | B85: Tests and independent checks | C85: Spot-check one analytic estimate by hand | D85: In by_audit_year.csv, pick EIPM national|gross, ratio, audit year 1. Confirm lower = estimate - 1.96 x se is consistent with the reported interval (se in estimates.parquet). | E85: eipm/estimation/results/base/estimates.parquet; by_audit_year.csv | F85: Consistent to rounding | G85: Pass | H85: 2026-10-21 | I85: Claude | J85: qa/Claude (see RERUN_SUMMARY.md, verification/, review/PEER_REVIEW.md) | L85: EIPM ratio, year 1: 0.0089691 − 1.96 × 0.0018337 = 0.0053750 = reported lower (to 7 decimals).
A86: F. Data security and disclosure
A87: F1 | B87: Data security and disclosure | C87: No protected health information or real unit-level data | D87: Confirm every population is generated from stated distributions (errors/sql) and no data files are read from outside the project. | E87: */errors/sql/*.sql; .gitignore (data/raw/ excluded) | F87: Only synthetic data | G87: Pass | H87: 2026-10-21 | I87: Claude | J87: qa/Claude (see RERUN_SUMMARY.md, verification/, review/PEER_REVIEW.md) | L87: Only synthetic data; no external reads.
A88: F2 | B88: Data security and disclosure | C88: No non-public material | D88: Confirm there are no contractor methodology plans, internal error data, or non-public CMS documents; non-public design values are labeled illustrative. | E88: configs (comments 'illustrative', 'NOT public'); literature-review references | F88: Public sources only; illustrative values labeled | G88: Pass | H88: 2026-10-21 | I88: Claude | J88: qa/Claude (see RERUN_SUMMARY.md, verification/, review/PEER_REVIEW.md) | L88: Illustrative values labeled; no non-public material found.
A89: F3 | B89: Data security and disclosure | C89: Sources for public figures are cited | D89: Confirm each public figure used for calibration is cited with a source. | E89: manuscript References; literature review References | F89: Every figure has a source | G89: Fail | H89: 2026-10-21 | I89: Claude | J89: qa/Claude (see RERUN_SUMMARY.md, verification/, review/PEER_REVIEW.md) | K89: I-12 | L89: Every calibration figure has a source and matches CMS. Reference problems: ED OIG report year/number; Humana reporter citation unverified; several orphan references; secondary sources where primary exist (details in review/PEER_REVIEW.md Part 1.3).
A90: F4 | B90: Data security and disclosure | C90: Author disclosures and approvals | D90: Confirm the funding, conflicts of interest and disclaimer section is completed, and any employer or agency clearance needed before publication has been obtained. | E90: manuscripts/sections/03_future_conclusion_refs.md | F90: Completed before submission (or noted as open) | G90: Fail | H90: 2026-10-21 | I90: Claude | J90: qa/Claude (see RERUN_SUMMARY.md, verification/, review/PEER_REVIEW.md) | K90: I-19 | L90: Affiliation, funding, conflicts and disclaimer are still bracketed placeholders; employer/agency clearance status not recorded.
A91: F5 | B91: Data security and disclosure | C91: License and repository contents | D91: Confirm a LICENSE file is present and the repository contains no credentials, personal data or large unexplained files. | E91: LICENSE; repository root | F91: As expected | G91: Pass | H91: 2026-10-21 | I91: Claude | J91: qa/Claude (see RERUN_SUMMARY.md, verification/, review/PEER_REVIEW.md) | L91: MIT LICENSE present; no credentials or personal data.
A92: G. Documentation and reproducibility
A93: G1 | B93: Documentation and reproducibility | C93: Start Here instructions worked as written | D93: Record any step that failed, was unclear, or needed a change on your operating system. | E93: start-here/README.md | F93: No changes needed, or each recorded on the Issues log | G93: Pass | H93: 2026-10-21 | I93: Claude | J93: qa/Claude (see RERUN_SUMMARY.md, verification/, review/PEER_REVIEW.md) | L93: Worked as written on Linux.
A94: G2 | B94: Documentation and reproducibility | C94: Run times are close to the published estimates | D94: Compare your stage times (Run log sheet) with start-here/README.md step 7. | E94: start-here/README.md; Run log sheet | F94: Recorded; large differences explained | G94: Pass | H94: 2026-10-21 | I94: Claude | J94: qa/Claude (see RERUN_SUMMARY.md, verification/, review/PEER_REVIEW.md) | L94: Stage times within 10% of published.
A95: G3 | B95: Documentation and reproducibility | C95: Every result traces to code and data in the repository | D95: Pick 3 numbers from the manuscript and follow each back to the file and code that produced it. | E95: manuscripts; shared/results; */estimation | F95: Each traced without gaps | G95: Pass | H95: 2026-10-21 | I95: Claude | J95: qa/Claude (see RERUN_SUMMARY.md, verification/, review/PEER_REVIEW.md) | L95: Three numbers traced: Part C 24/25 (results/base/metrics.json → by_scenario.csv → Table 2); PERM ±0.63 half-width (tables.md); Part D 37% (build_tables.py sp ratio).
A96: G4 | B96: Documentation and reproducibility | C96: Data dictionary describes the output files | D96: Spot-check 5 columns in estimates.parquet and by_scenario.csv against the data dictionary. | E96: shared/data_dictionary.md | F96: Definitions match | G96: Fail | H96: 2026-10-21 | I96: Claude | J96: qa/Claude (see RERUN_SUMMARY.md, verification/, review/PEER_REVIEW.md) | K96: I-09 | L96: data_dictionary.md:110 describes PERM strata as equal-dollar per state x quarter x type (code: equal-count quintiles per state x type); Part C population columns missing_doc, add_fam, add_coef not documented. Other spot-checked columns match.
A97: H. Close-out and sign-off
A98: H1 | B98: Close-out and sign-off | C98: Every Fail is on the Issues log | D98: Check that each row marked Fail has an issue ID in the Issue ID column. | E98: Checklist; Issues log | F98: Yes | G98: Pass | H98: 2026-10-21 | I98: Claude | J98: qa/Claude (see RERUN_SUMMARY.md, verification/, review/PEER_REVIEW.md) | L98: Every Fail row carries an issue ID.
A99: H2 | B99: Close-out and sign-off | C99: Issues are resolved or accepted | D99: Confirm no Critical or Major issue is Open. Minor issues may remain open if noted on the sign-off form. | E99: Issues log; Summary sheet | F99: No open Critical or Major issues | G99: Pass | H99: 2026-10-21 | I99: Claude | J99: qa/Claude (see RERUN_SUMMARY.md, verification/, review/PEER_REVIEW.md) | L99: Major issues I-02 to I-05 are Open pending the author's decisions; not ready to sign.
A100: H3 | B100: Close-out and sign-off | C100: Completed checklist saved in the re-run folder | D100: Save this workbook as QA_Checklist_<date>_<initials>.xlsx in qa/reruns/<date>_<initials>/review/. | E100: qa/reruns/<date>_<initials>/review/ | F100: Saved | G100: Pass | H100: 2026-10-21 | I100: Claude | J100: qa/Claude (see RERUN_SUMMARY.md, verification/, review/PEER_REVIEW.md) | L100: Saved in qa/Claude/review/.
A101: H4 | B101: Close-out and sign-off | C101: Sign-off form completed and saved | D101: Complete qa/QA_Signoff_Template.docx, sign it, and save it (and a PDF) in the review/ folder. | E101: qa/reruns/<date>_<initials>/review/ | F101: Signed and saved | G101: N/A | H101: 2026-10-21 | I101: Claude | J101: qa/Claude (see RERUN_SUMMARY.md, verification/, review/PEER_REVIEW.md) | L101: Not signed: an AI reviewer cannot attest. The form is left for the human co-reviewer; findings are in review/PEER_REVIEW.md.
A102: H5 | B102: Close-out and sign-off | C102: Re-run folder submitted | D102: Submit the qa/reruns/<date>_<initials>/ folder to the project (pull request or ZIP to the author). | E102: qa/README.md, step 9 | F102: Submitted; date recorded | G102: Pass | H102: 2026-10-21 | I102: Claude | J102: qa/Claude (see RERUN_SUMMARY.md, verification/, review/PEER_REVIEW.md) | L102: Submitted as qa/Claude/ in this repository.

Sheet Run log
A1: Run log
A2: One row per run folder in start-here/logs/ (copy from RERUN_SUMMARY.md and run_log.txt). Duration is calculated.
A4: Run folder name | B4: Run type | C4: Stages run | D4: Started (YYYY-MM-DD HH:MM) | E4: Finished (YYYY-MM-DD HH:MM) | F4: Duration (h:mm) | G4: Outcome | H4: Result check | I4: Notes
A5: run_2026-10-21_145457_quick | B5: Quick trial | C5: 1-2 | D5: 2026-10-21 14:54 | E5: 2026-10-21 14:57 | F5: =IF(AND(ISNUMBER(D5),ISNUMBER(E5)),E5-D5,"") | G5: Finished | H5: N/A (trial) | I5: Your setup works.
A6: run_2026-10-21_145729 | B6: Full replication | C6: 1-3 (interrupted) | D6: 2026-10-21 14:57 | E6: 2026-10-21 16:57 | F6: =IF(AND(ISNUMBER(D6),ISNUMBER(E6)),E6-D6,"") | G6: Interrupted in stage 3 | H6: n/a | I6: Stopped by the reviewer's background-process time limit during CERT fixed-rate run
A7: run_2026-10-21_165745 | B7: Full replication (resumed) | C7: 3 | D7: 2026-10-21 16:57 | E7: 2026-10-21 18:00 | F7: =IF(AND(ISNUMBER(D7),ISNUMBER(E7)),E7-D7,"") | G7: Finished | H7: n/a | I7: --only 3
A8: run_2026-10-21_180449 | B8: Full replication (resumed) | C8: 4-8 | D8: 2026-10-21 18:04 | E8: 2026-10-21 19:04 | F8: =IF(AND(ISNUMBER(D8),ISNUMBER(E8)),E8-D8,"") | G8: Finished | H8: REPRODUCED EXACTLY | I8: --from 4; 183/183 files identical; 38 tests passed
F9: =IF(AND(ISNUMBER(D9),ISNUMBER(E9)),E9-D9,"")
F10: =IF(AND(ISNUMBER(D10),ISNUMBER(E10)),E10-D10,"")
F11: =IF(AND(ISNUMBER(D11),ISNUMBER(E11)),E11-D11,"")
F12: =IF(AND(ISNUMBER(D12),ISNUMBER(E12)),E12-D12,"")
F13: =IF(AND(ISNUMBER(D13),ISNUMBER(E13)),E13-D13,"")
F14: =IF(AND(ISNUMBER(D14),ISNUMBER(E14)),E14-D14,"")
F15: =IF(AND(ISNUMBER(D15),ISNUMBER(E15)),E15-D15,"")
F16: =IF(AND(ISNUMBER(D16),ISNUMBER(E16)),E16-D16,"")
A19: Stage run times (full replication)
A20: Stage | B20: Description | D20: Published time (2 cores, 8 GB) | E20: Your time (h:mm:ss) | G20: Notes
A21: 1 | B21: Build the synthetic populations | D21: 0.0008912037 | E21: 0:01:17
A22: 2 | B22: Estimate: parametric-rate bootstrap (reported) | D22: 0.0475 | E22: 1:05:15
A23: 3 | B23: Estimate: fixed-rate bootstrap (comparison) | D23: 0.050219907 | E23: 1:02:59
A24: 4 | B24: Part D pre-IRA reference | D24: 0.047835648 | E24: 0:58:23
A25: 5 | B25: Join estimates to the truth | D25: 1.1574074e-05 | E25: 0:00:01
A26: 6 | B26: Manuscript tables and figures | D26: 2.3148148e-05 | E26: 0:00:04
A27: 7 | B27: Automated tests | D27: 0.00071759259 | E27: 0:01:00
A28: 8 | B28: Result check | D28: 1.1574074e-05 | E28: 0:00:03
B29: Total | D29: =SUM(D21:D28) | E29: =SUM(E21:E28)
A30: Published times: measured on the author's test re-run, 2026-10-20 (start-here/README.md, step 7). Enter your times from run_log.txt ('Stage N finished in ...').

Sheet Issues log
A1: Issues log
A2: One row per problem found. Use the ID (I-01, I-02, ...) in the Checklist's Issue ID column.
A4: Issue ID | B4: Date found | C4: Checklist ID | D4: Severity | E4: Description | F4: File / location | G4: How found | H4: Status | I4: Resolution | J4: Date resolved | K4: Resolved by
A5: I-01 | B5: 2026-10-21 | C5: C21 | D5: Minor | E5: Part C errors/config.yaml design block lists 1,500 enrollees per stratum; the estimation uses 330 per tercile (990). Confirmed. | F5: part-c-ipm/errors/config.yaml:39-42 | G5: Code review | H5: Open | I5: Metadata only; correct the description.
A6: I-02 | B6: 2026-10-21 | C6: C16 | D6: Major | E6: Part C simulation kernel applies audited addition rates to recipients that also received HCC failures in the iteration and nets the two; the population applies additions only when no overpayment and no missing documentation. Simulated underpayments run ~8% below the kernel's linear expectation (committed mean 49.3 bp vs truth 57.4; analytic 54-55); over and gross biased down ~0.8% / 1.5%. | F6: part-c-ipm/estimation/simulation.py:137-143 vs errors/sql/04_apply_errors.sql:125 | G6: Code review + standalone check (review/scripts/agent_b/q8.py) | H6: Open | I6: Apply additions only to recipients with no failure, or redefine the addition-rate denominator; add per-domain unbiasedness test; re-run Part C.
A7: I-03 | B7: 2026-10-21 | C7: C37, D14 | D7: Major | E7: Approximate Monte Carlo over 2,000 Part C and 300 EIPM re-drawn audits: the true SD of the simulation's (linearized) point estimator is 50.8 bp (Part C) / 17.8 bp (EIPM) vs reported parametric SE 47.2 / 16.1, while the ratio SE matches its exact design SE. Parametric interval ~7-10% too narrow for its own estimator; implies ~92-93% coverage, indistinguishable from 95% with 25 audit years; audit-size shares would be ~86% / 92% not 79% / 80%. | F7: part-c-ipm/estimation/simulation.py:104,126-133; eipm/estimation/simulation.py:94,114 | G7: Standalone check (review/scripts/agent_b/q7.py, q9.py) | H7: Open | I7: Run ≥200 audit years and report half-width ÷ (1.96 × empirical SD) and coverage with Monte Carlo SE; consider resampling error sizes and modeling rate correlation.
A8: I-04 | B8: 2026-10-21 | C8: D14 | D8: Major | E8: The simulation's width and point-accuracy advantage depends on error probability and size being independent of payment within strata, which is true by construction in every population; the simulation borrows count rates and takes sizes from the population while the analytic estimators are dollar-weighted. Explains the Part D 5x point-SD gap (specialty PDEs are 31-33% of error dollars). | F8: */errors/sql/*apply_errors*.sql (e.g. part-d 04_apply_errors.sql:8; cert_02_apply_errors.sql:18) | G8: Code review + standalone check (review/scripts/agent_c/q2.py) | H8: Open | I8: Add a robustness scenario (payment-dependent error probability, size-correlated taints, optional clustering) as a sub-folder and Appendix D; state the assumption for all programs in B.6.3; present the gain as model-based.
A9: I-05 | B9: 2026-10-21 | C9: C26, D14 | D9: Major | E9: Part D has no fair same-audit analytic comparator: ratio/regression use a 990-beneficiary audit that reviews ~41,000 PDEs; the PDE-audit "expansion" is a uniform-haircut plug-in whose delta-method SE understates its own SD (0.37 vs 0.54 pts). §4.1 and §4.3 misdescribe the cause of its bias and the width of its interval. | F9: part-d-ipm/estimation/simulation.py:227-253 | G9: Code review | H9: Open | I9: Implement a PDE-level HT/ratio comparator using each audited PDE's marginal Medicare-payment effect, or remove the Part D width comparison (63% / 37%) from the Abstract and Conclusion.
A10: I-06 | B10: 2026-10-21 | C10: C15 | D10: Minor | E10: Parametric redraw draws q~ = Binomial(f,q)/f with the observed f rather than the redrawn f~. | F10: part-d simulation.py:204; perm_simulation.py:94; cert_simulation.py:197 | G10: Code review | H10: Open | I10: Draw f~ first, or restate §3.6 as conditional on observed f.
A11: I-07 | B11: 2026-10-21 | C11: C11, C12 | D11: Minor | E11: Regression df subtracts intercepts twice (negligible at n=990); the <10-errors fallback counts errors in any domain, not the domain being estimated. | F11: shared/ipsim/regression.py:82,92,110 | G11: Code review | H11: Open | I11: df = n − terms; count errors per domain or document the rule as implemented.
A12: I-08 | B12: 2026-10-21 | C12: C2 | D12: Minor | E12: README.md:14 describes a "beneficiary sample (108,000 beneficiaries)" (the population) and says the simulation fixes a beneficiary sample; simulation.py docstring says the same. Code: SRS of 990 for ratio/regression; simulation uses the PDE audit only. | F12: README.md:14; shared/ipsim/simulation.py:27-28 | G12: Code review | H12: Open | I12: Correct both.
A13: I-09 | B13: 2026-10-21 | C13: C30, G4 | D13: Minor | E13: PERM documentation (README:17, perm.yaml:46 "equal across quarters and strata", perm_01_population.sql header, data_dictionary.md:110) describes equal-dollar strata within state × quarter × type; code builds equal-count quintiles within state × type, no quarter, Neyman. Also README:40 attributes the systematic-as-SRS variance note to CERT. | F13: perm-cert/README.md:17,40; perm-cert/errors/perm.yaml:46; shared/data_dictionary.md:110 | G13: Code review | H13: Open | I13: Align docs with code (design.yaml is written from perm.yaml:design).
A14: I-10 | B14: 2026-10-21 | C14: C14, C22 | D14: Minor | E14: Manuscript §3.5 step 2, §3.6 and A.5 step 4 say partial sizes are drawn uniformly from the audited list; the Part C kernel applies the HCC mean audited loss (B.1 says so). §5.3 "two binomial draws per stratum" is 30 draws per iteration in Part C. §3.5 "equivalent to a uniformly drawn donor" does not hold for Part C. | F14: part-c-ipm/estimation/simulation.py:104,133; manuscript §3.5, §3.6, §5.3, A.5 | G14: Code review | H14: Open | I14: Correct the method sections.
A15: I-11 | B15: 2026-10-21 | C15: D15, C23, C24 | D15: Minor | E15: Assumptions in code not stated: error independence from payment applies to Part C and Part D (B.6.3); Part D strata/sizes are illustrative (§3.2); all LIS pay $4.90/$12.15; MDP affects plan liability only; brand/specialty independent; direct subsidy constant; PERM whole-year eligibility propagated by the simulation; one FMAP per state; CERT error independent of stratum; underpayments all partial; Part C addition rule, hierarchy-move share, chart-review multiplier, coding intensity, probability cap; EIPM population and income-ratio rules. Full list in review/PEER_REVIEW.md Part 2.4. | F15: Appendix B | G15: Code review | H15: Open | I15: Add to Appendix B.
A16: I-12 | B16: 2026-10-21 | C16: F3 | D16: Minor | E16: References: ED OIG "FY 2025" report is the FY 2024 report (A25DC0225); FY 2025 is A26DC0288 (2026). "Humana v. Becerra, 801 F. Supp. 3d 624" reporter cite unverified. CMS 2025a fact sheet is dated Jan 15, 2026. GAO 2026 needs its number (GAO-26-108694). Orphans: Biddle 1990, Davison & Hinkley 1997, King & Madansky 2013, Rao & Wu 1988, Wolter 2007, CMS 2025d/2026a/2026b/2024. Missing entry for P.L. 119-21. §1.3 cross-reference should be §4.2. Secondary sources (MyChesCo, Milliman, STAT, BPC, conference bio) where primary exist. Several characterizations of Edwards et al. 2023, Kvanli & Schauer, Kolenikov and Liu 2025 over-read (details in review/review_citations.md). | F16: manuscript References; literature review §3-§6 and References | G16: Citation verification (web) | H16: Open | I16: Apply corrections in review/PEER_REVIEW.md Part 1.3.
... A23: I-19 | B23: 2026-10-21 | C23: F4 | D23: Minor | E23: Affiliation, funding, conflicts of interest and disclaimer are bracketed placeholders; employer/agency clearance not recorded. | F23: manuscripts/sections/00_front.md, 03_future_conclusion_refs.md | G23: Review | H23: Open | I23: Complete before circulation.
A41: Severity: Critical = a reported result is wrong or cannot be reproduced. Major = an assumption or method differs from its description in a way that could change a result. Minor = documentation or labeling error with no effect on results. Note = suggestion. Status 'Accepted' = left open by agreement, explained in Resolution. Row 5 is an example (a real discrepancy, also listed as Checklist C21). If you confirm it, delete '(EXAMPLE)' from its ID so it is counted; otherwise overwrite the row.
